os_package_registry/__init__.py
os_package_registry/package_registry.py
os_package_registry-0.0.21.dist-info/LICENSE
os_package_registry-0.0.21.dist-info/METADATA
os_package_registry-0.0.21.dist-info/WHEEL
os_package_registry-0.0.21.dist-info/top_level.txt
os_package_registry-0.0.21.dist-info/RECORD
