Metadata-Version: 2.1
Name: os-package-registry
Version: 0.0.21
Summary: Manage a registry of packages on an ElasticSearch instance
Home-page: https://github.com/openspending/os-package-registry
Author: Open Knowledge International
Author-email: info@okfn.org
License: MIT
Keywords: fdp fiscal data package openspending elasticsearch
Platform: UNKNOWN
Classifier: Development Status :: 4 - Beta
Classifier: Intended Audience :: Developers
Classifier: Intended Audience :: Information Technology
Classifier: Topic :: Utilities
Classifier: License :: OSI Approved :: MIT License
Classifier: Programming Language :: Python :: 3
Classifier: Programming Language :: Python :: 3.6
Requires-Dist: elasticsearch (<6.0.0,>=5.0.0)
Requires-Dist: os-api-cache (>=0.0.7)
